meshwork/__init__.py
meshwork/client_ops.py
meshwork/config.py
meshwork/funcs.py
meshwork/source_types.py
meshwork/auth/__init__.py
meshwork/auth/authorization.py
meshwork/auth/generate_token.py
meshwork/auth/roles.py
meshwork/automation/__init__.py
meshwork/automation/adapters.py
meshwork/automation/automations.py
meshwork/automation/models.py
meshwork/automation/publishers.py
meshwork/automation/utils.py
meshwork/automation/worker.py
meshwork/automation/workflow.py
meshwork/compile/__init__.py
meshwork/compile/rpsc.py
meshwork/executors/__init__.py
meshwork/executors/compose.py
meshwork/executors/inference.py
meshwork/executors/sop.py
meshwork/models/__init__.py
meshwork/models/assets.py
meshwork/models/contexts.py
meshwork/models/houClasses.py
meshwork/models/houTypes.py
meshwork/models/params.py
meshwork/models/sessions.py
meshwork/models/streaming.py
meshwork/runtime/__init__.py
meshwork/runtime/alerts.py
meshwork/runtime/decorators.py
meshwork/runtime/files.py
meshwork/runtime/params.py
meshwork/runtime/services.py
meshwork/sources/__init__.py
meshwork/sources/memory.py
meshwork-0.1.2.dist-info/METADATA
meshwork-0.1.2.dist-info/WHEEL
meshwork-0.1.2.dist-info/entry_points.txt
meshwork-0.1.2.dist-info/RECORD
